funleaker/__init__.cp313-win_amd64.pyd
funleaker/security.cp313-win_amd64.pyd
funleaker/syn_utils.cp313-win_amd64.pyd
funleaker-1.4.4.dist-info/licenses/LICENSE
funleaker-1.4.4.dist-info/METADATA
funleaker-1.4.4.dist-info/WHEEL
funleaker-1.4.4.dist-info/entry_points.txt
funleaker-1.4.4.dist-info/top_level.txt
funleaker-1.4.4.dist-info/RECORD
