Metadata-Version: 2.4
Name: Funleaker
Version: 1.4.4
Summary: This is the official funleaker core functions (beta) for Python. Users can now log in to their Syn account and use basic functions. This can be included in your web API app. This project is NSFW, and all results will return NSFW content. Please be aware.
Author: Syn_Tw
Author-email: announmoseemail@notreal.com
License: Custom License (Non-Commercial Use Only)
Classifier: Programming Language :: Python :: 3
Classifier: License :: Other/Proprietary License
Classifier: Operating System :: OS Independent
Requires-Python: >=3.6
License-File: LICENSE
Requires-Dist: requests
Requires-Dist: tqdm
Requires-Dist: colorama
Requires-Dist: platformdirs
Dynamic: author
Dynamic: author-email
Dynamic: classifier
Dynamic: description
Dynamic: description-content-type
Dynamic: license
Dynamic: license-file
Dynamic: requires-dist
Dynamic: requires-python
Dynamic: summary
